ywh_program_selector/YesWeHackApi.py
ywh_program_selector/__init__.py
ywh_program_selector/auth.py
ywh_program_selector/config.py
ywh_program_selector/utils.py
ywh_program_selector/ywh_program_selector.py
ywh_program_selector-0.1.4.dist-info/METADATA
ywh_program_selector-0.1.4.dist-info/WHEEL
ywh_program_selector-0.1.4.dist-info/entry_points.txt
ywh_program_selector-0.1.4.dist-info/top_level.txt
ywh_program_selector-0.1.4.dist-info/RECORD
