Metadata-Version: 2.4
Name: ywh_program_selector
Version: 0.1.4
Summary: The ywh_program_selector project is a tool designed to help users manage and prioritize their YesWeHack (YWH) private programs
Home-page: https://github.com/jdouliez/ywh_program_selector
Author: @_Ali4s_
Author-email: jordan.douliez@gmail.com
Classifier: Programming Language :: Python :: 3
Classifier: License :: OSI Approved :: MIT License
Classifier: Operating System :: OS Independent
Requires-Python: >=3.6
Requires-Dist: requests
Requires-Dist: tqdm
Requires-Dist: prettytable
Requires-Dist: colorama
Requires-Dist: pyotp
Requires-Dist: unidecode
Dynamic: author
Dynamic: author-email
Dynamic: classifier
Dynamic: description
Dynamic: description-content-type
Dynamic: home-page
Dynamic: requires-dist
Dynamic: requires-python
Dynamic: summary
